{"vhc60rfBN989sYdDtShNeA==":"menu-122x122.png","brZuyh1xh1LvtlIHNnk+3g==":"valor-2000x3000.jpg","x6Y4mpigb7xn34hTvGjM6w==":"8-1710x962.png","oCxOUxe0ZjZw9p40PPpzzQ==":"12-1024x576.png","VUBRDUsEcrJXRnOhD7ih/A==":"guanajuato-2000x2500.jpg","KqI0mxmKfZtChsCuDxFudQ==":"9-1368x770.png","VbSzqqRoBOXs0SfWEMMhVQ==":"visi%C3%B3n%20de%20trabajo-2000x2667.jpg","CHwJ5MRuhk/M0rgSzP4u/Q==":"erik-eastman-293362-unsplash-2000x3000.jpg","CUuf7s/p3q+YfUCSl4Sowg==":"dr.%20felipe%20moreno%20yebra-765x350.jpg","M//kQuUhH64UfkFFzqUwlA==":"secretar%C3%ADa%20de%20finanzas%20de%20slp2-680x450.png","tkmXtftGuSc+WUumuY/QJw==":"euroamericana%20de%20calzado2-680x450.png","MdL/Hzt8ceWe/VULX4SRhg==":"swissmex2-680x450.png","RDK7dEmoX2/Sx+pSOVCk3Q==":"pirelli2-680x450.png","X4Im4ftp5qlJ8FDbNX1L+w==":"novares2-680x450.png","Wf2TeRC/6OK3LumpEckJdA==":"andrew-childress-103062-unsplash-2000x1333.jpg","srWTNozF1hm16xw0/dKHhQ==":"6-952x536.png","kFAvdcs/NLZExMyal2B46w==":"ricardo-gomez-angel-402945-unsplash-2000x2666.jpg","bM/+eISidQD1Ab+JAG2J8w==":"3-952x536.png","UAc7kepzJPkrSn4uqTRvmw==":"background4.jpg","ocvqCwjPPwEUfv0rbNzHvA==":"2-952x536.png","//BYgggZCb8nw2khU8RDWg==":"5-952x536.png","zXC3h5TfWopfq4vZF+4lIg==":"4-952x536.png","pSucUAkP+g81rv6JzANAYw==":"1-952x536.png","iU/gOfXRK7F3ZETlMGp4kQ==":"7-952x536.png","F48B5zSgsizqrUxhUEgk0w==":"10-2000x1125.png","ziMzxrpTEdIN+G0PJlscZQ==":"11-2000x1125.png","83HZdBjsSw/lKEd6KTegXA==":"11-1-2000x1125.png","sT80Y4RCGNBrSInGgrjIuA==":"background3.jpg","VfG+u5xUhWbJWB5MW/EHkQ==":"experiencia%20-2000x3000.jpg","FhdU6Er9rCCtogARC1t9kg==":"mbr-1920x1202.jpg","U0s3KttwjwYaAHoJPwftjA==":"ags-745x412.jpg","OnwFaYSsrnh80hayAaITvg==":"cdmx-630x472.jpg","tRVoaL0IemX/ow+JiEZ4Aw==":"cancun-800x363.jpg","Jg2SwsY3avKbHPajGgZGeg==":"leon-1023x471.jpg","8PoRd5gkQl/wE6Y3Bg3fZQ==":"mbr-1920x1440.jpg","Srxphkwwv1Tef07NN2uchw==":"favicon-128x128.png","BxTv1Fis+p0uN6zsINQYjg==":"logotipo-png-1.png","hJ4cMD6xSdpvBrhg20krFQ==":"menu.png","35HhplLAXyqCKMrp2iczXw==":"ags.jpg","f3A2vIFugLz/9JLefsHvtA==":"cdmx.jpg","/OGGW/FWr+aV+5OWdBUgqg==":"leon.jpg","vcWCOWBFs1Al4y9EC7vCkQ==":"leon.jpeg","AQFCo1l565/rym1+WYuwMg==":"6.png","sC1gclJFIMUAcsRz4Zq6Sw==":"7.png"}